reflex_cli/__init__.py
reflex_cli/cli.py
reflex_cli/deployments.py
reflex_cli/constants/__init__.py
reflex_cli/constants/base.py
reflex_cli/constants/compiler.py
reflex_cli/constants/hosting.py
reflex_cli/core/__init__.py
reflex_cli/core/config.py
reflex_cli/utils/__init__.py
reflex_cli/utils/console.py
reflex_cli/utils/dependency.py
reflex_cli/utils/exceptions.py
reflex_cli/utils/hosting.py
reflex_cli/v2/__init__.py
reflex_cli/v2/apps.py
reflex_cli/v2/cli.py
reflex_cli/v2/deployments.py
reflex_cli/v2/project.py
reflex_cli/v2/secrets.py
reflex_cli/v2/utils.py
reflex_cli/v2/vmtypes_regions.py
reflex_hosting_cli-0.1.60.dist-info/METADATA
reflex_hosting_cli-0.1.60.dist-info/WHEEL
reflex_hosting_cli-0.1.60.dist-info/licenses/LICENSE
reflex_hosting_cli-0.1.60.dist-info/RECORD
